vpnetbox/__init__.py
vpnetbox/branch.py
vpnetbox/connectors/__init__.py
vpnetbox/connectors/base_c.py
vpnetbox/connectors/base_ca.py
vpnetbox/connectors/circuits.py
vpnetbox/connectors/core.py
vpnetbox/connectors/dcim.py
vpnetbox/connectors/extras.py
vpnetbox/connectors/ipam.py
vpnetbox/connectors/plugins_ca.py
vpnetbox/connectors/status.py
vpnetbox/connectors/tenancy.py
vpnetbox/connectors/users.py
vpnetbox/connectors/virtualization.py
vpnetbox/connectors/wireless.py
vpnetbox/exceptions.py
vpnetbox/foragers/__init__.py
vpnetbox/foragers/base_f.py
vpnetbox/foragers/base_fa.py
vpnetbox/foragers/circuits.py
vpnetbox/foragers/core.py
vpnetbox/foragers/dcim.py
vpnetbox/foragers/extras.py
vpnetbox/foragers/ipam.py
vpnetbox/foragers/tenancy.py
vpnetbox/foragers/users.py
vpnetbox/foragers/virtualization.py
vpnetbox/foragers/wireless.py
vpnetbox/helpers.py
vpnetbox/log.py
vpnetbox/messages.py
vpnetbox/nb_cache.py
vpnetbox/nb_tree.py
vpnetbox/py.typed
vpnetbox/types_.py
vpnetbox/wrappers.py
vpnetbox-2.5.13.dist-info/METADATA
vpnetbox-2.5.13.dist-info/WHEEL
vpnetbox-2.5.13.dist-info/RECORD
