Metadata-Version: 2.1
Name: vpnetbox
Version: 2.5.13
Summary: Python package to work with Netbox using REST API
Home-page: https://github.com/vladimirs-git/vpnetbox
License: Apache-2.0
Keywords: netbox
Author: Vladimirs Prusakovs
Author-email: vladimir.prusakovs@gmail.com
Requires-Python: >=3.8,<4.0
Classifier: Development Status :: 4 - Beta
Classifier: Intended Audience :: Developers
Classifier: License :: OSI Approved :: Apache Software License
Classifier: Natural Language :: English
Classifier: Programming Language :: Python :: 3
Classifier: Programming Language :: Python :: 3.8
Classifier: Programming Language :: Python :: 3.9
Classifier: Programming Language :: Python :: 3.10
Classifier: Programming Language :: Python :: 3.11
Provides-Extra: test
Requires-Dist: pydantic (>=2,<3)
Requires-Dist: requests (>=2,<3)
Requires-Dist: vhelpers (>=0.1,<0.2)
Project-URL: Bug Tracker, https://github.com/vladimirs-git/vpnetbox/issues
Project-URL: Download URL, https://github.com/vladimirs-git/vpnetbox/archive/refs/tags/2.5.13.tar.gz
Project-URL: Repository, https://github.com/vladimirs-git/vpnetbox
